{
	"downloads":
	[
		{
			"label_pre": "Short Structure<div class='br05'></div>",
			"label": "Cover Letter<div class='br05'></div>",
			"label_post": "[ Format: html ]<div class='br05'></div>",
			"url": "https://canerozdemircgi.github.io/Resume/index.html?path=index-1-short"
		},
		{
			"label_pre": "Long Structure<div class='br05'></div>",
			"label": "Cover Letter<div class='br05'></div>",
			"label_post": "[ Format: html ]<div class='br20'></div>",
			"url": "https://canerozdemircgi.github.io/Resume/index.html?path=index-1-long"
		},
		{
			"label_pre": "Development<div class='br05'></div>",
			"label": "Cover Letter<div class='br05'></div>",
			"label_post": "[ Source Code ]",
			"url": "https://github.com/canerozdemircgi/Resume"
		}
	]
}